cockroach_migrator/__init__.py
cockroach_migrator/cli.py
cockroach_migrator/migrate.py
cockroach_migrator/migrate_cockroach.py
cockroach_migrator/migrate_conversion.py
cockroach_migrator/migrate_postgresql.py
cockroach_migrator/migrate_validate.py
cockroach_migrator/config/migration_config.json
cockroach_migrator/templates/migration_config.json
cockroach_migrator-0.1.0.dist-info/licenses/LICENSE
cockroach_migrator-0.1.0.dist-info/METADATA
cockroach_migrator-0.1.0.dist-info/WHEEL
cockroach_migrator-0.1.0.dist-info/entry_points.txt
cockroach_migrator-0.1.0.dist-info/top_level.txt
cockroach_migrator-0.1.0.dist-info/RECORD
