Metadata-Version: 2.4
Name: cockroach-migrator
Version: 0.1.0
Summary: A comprehensive tool for migrating data from CockroachDB to PostgreSQL
Home-page: https://github.com/nomos-oss/cockroach-migrator
Author: Nomos
Author-email: Nomos <oss@ordicio.com>
Maintainer-email: Nomos <oss@ordicio.com>
License-Expression: MIT
Project-URL: Homepage, https://github.com/nomos-oss/cockroach-migrator
Project-URL: Documentation, https://github.com/nomos-oss/cockroach-migrator#readme
Project-URL: Repository, https://github.com/nomos-oss/cockroach-migrator.git
Project-URL: Bug Tracker, https://github.com/nomos-oss/cockroach-migrator/issues
Keywords: cockroachdb,postgresql,migration,database,backup,restore
Classifier: Development Status :: 4 - Beta
Classifier: Intended Audience :: Developers
Classifier: Intended Audience :: System Administrators
Classifier: Operating System :: OS Independent
Classifier: Programming Language :: Python :: 3
Classifier: Programming Language :: Python :: 3.7
Classifier: Programming Language :: Python :: 3.8
Classifier: Programming Language :: Python :: 3.9
Classifier: Programming Language :: Python :: 3.10
Classifier: Programming Language :: Python :: 3.11
Classifier: Programming Language :: Python :: 3.12
Classifier: Topic :: Database
Classifier: Topic :: Database :: Database Engines/Servers
Classifier: Topic :: System :: Archiving :: Backup
Classifier: Topic :: Utilities
Requires-Python: >=3.7
License-File: LICENSE
Requires-Dist: requests>=2.25.0
Requires-Dist: psycopg2-binary>=2.8.0
Provides-Extra: dev
Requires-Dist: pytest>=6.0; extra == "dev"
Requires-Dist: pytest-cov>=2.0; extra == "dev"
Requires-Dist: black>=21.0; extra == "dev"
Requires-Dist: flake8>=3.8; extra == "dev"
Requires-Dist: mypy>=0.800; extra == "dev"
Provides-Extra: test
Requires-Dist: pytest>=6.0; extra == "test"
Requires-Dist: pytest-cov>=2.0; extra == "test"
Dynamic: author
Dynamic: home-page
Dynamic: license-file
Dynamic: requires-python
